<configuration>
    <domain>
        
        <nodeSize> 0.25  </nodeSize>

        
        <nodeRatio>
            <x> 16 </x>
            <y> 4 </y>
            <z> 1 </z>
        </nodeRatio>

        <boundaryConditions>
            <material>
                
                <west>ZeroGradient</west>
                <east>ZeroGradient</east>
                <south>ZeroGradient</south>
                <north>ZeroGradient</north>
                <bottom>Symmetry</bottom>
                <top>Symmetry</top>
            </material>

            <levelSet>
                
                <west>   symmetry </west>
                <east>   symmetry </east>
                <south>  symmetry </south>
                <north>  symmetry </north>
                <bottom> symmetry </bottom>
                <top>    symmetry </top>
            </levelSet>
        </boundaryConditions>

        <initialConditions>
            <material1>
	        if (sqrt((x-0.5)^2 + (y-0.5)^2) &lt; 0.2)
       	 {
       	 	if (x &gt; 0.5 &amp; y &gt; 0.5)
       	 	{
	       	 	density := 1.0;
				velocityX := -5.0 * sqrt((x-0.5)^2 + (y-0.5)^2) * sin(atan((y - 0.5) / (x - 0.5))) + 1.0;
				velocityY := 5.0 * sqrt((x-0.5)^2 + (y-0.5)^2) * cos(atan((y - 0.5) / (x - 0.5)));
				velocityZ := 0.0;
				pressure := 5.0 + 12.5 * ((x-0.5)^2 + (y-0.5)^2);
       	 	}
       	 	else if (x &lt; 0.5 &amp; y &gt; 0.5)
       	 	{
	       	 	density := 1.0;
				velocityX := -5.0 * sqrt((x-0.5)^2 + (y-0.5)^2) * sin(atan(abs(y - 0.5) / abs(x - 0.5))) + 1.0;
				velocityY := -5.0 * sqrt((x-0.5)^2 + (y-0.5)^2) * cos(atan((y - 0.5) / (x - 0.5)));
				velocityZ := 0.0;
				pressure := 5.0 + 12.5 * ((x-0.5)^2 + (y-0.5)^2);
       	 	}
       	 	else if (x &lt; 0.5 &amp; y &lt; 0.5)
       	 	{
	       	 	density := 1.0;
				velocityX := -5.0 * sqrt((x-0.5)^2 + (y-0.5)^2) * sin(atan(-(y - 0.5) / (x - 0.5))) + 1.0;
				velocityY := -5.0 * sqrt((x-0.5)^2 + (y-0.5)^2) * cos(atan((y - 0.5) / (x - 0.5)));
				velocityZ := 0.0;
				pressure := 5.0 + 12.5 * ((x-0.5)^2 + (y-0.5)^2);
       	 	}
       	 	else
       	 	{
       	 		density := 1.0;
				velocityX := -5.0 * sqrt((x-0.5)^2 + (y-0.5)^2) * sin(atan((y - 0.5) / (x - 0.5))) + 1.0;
				velocityY := 5.0 * sqrt((x-0.5)^2 + (y-0.5)^2) * cos(atan((y - 0.5) / (x - 0.5)));
				velocityZ := 0.0;
				pressure := 5.0 + 12.5 * ((x-0.5)^2 + (y-0.5)^2);
       	 	}
        	}
        	else if (sqrt((x-0.5)^2 + (y-0.5)^2) &gt; 0.2 &amp; sqrt((x-0.5)^2 + (y-0.5)^2) &lt; 0.4)
        	{
       	 	if (x &gt; 0.5 &amp; y &gt; 0.5)
       	 	{
	       	 	density := 1.0;
				velocityX := -(2.0 - 5.0 * sqrt((x-0.5)^2 + (y-0.5)^2)) * sin(atan((y - 0.5) / (x - 0.5))) + 1.0;
				velocityY := (2.0 - 5.0 * sqrt((x-0.5)^2 + (y-0.5)^2)) * cos(atan((y - 0.5) / (x - 0.5)));
				velocityZ := 0.0;
				pressure := 9.0 - 4.0 * log(0.2) + 12.5 * ((x-0.5)^2 + (y-0.5)^2) - 20.0 * sqrt((x-0.5)^2 + (y-0.5)^2) + 4.0 * log(sqrt((x-0.5)^2 + (y-0.5)^2));
       	 	}
       	 	else if (x &lt; 0.5 &amp; y &gt; 0.5)
       	 	{
	       	 	density := 1.0;
				velocityX := -(2.0 - 5.0 * sqrt((x-0.5)^2 + (y-0.5)^2)) * sin(atan(abs(y - 0.5) / abs(x - 0.5))) + 1.0;
				velocityY := -(2.0 - 5.0 * sqrt((x-0.5)^2 + (y-0.5)^2)) * cos(atan((y - 0.5) / (x - 0.5)));
				velocityZ := 0.0;
				pressure := 9.0 - 4.0 * log(0.2) + 12.5 * ((x-0.5)^2 + (y-0.5)^2) - 20.0 * sqrt((x-0.5)^2 + (y-0.5)^2) + 4.0 * log(sqrt((x-0.5)^2 + (y-0.5)^2));
       	 	}
       	 	else if (x &lt; 0.5 &amp; y &lt; 0.5)
       	 	{
	       	 	density := 1.0;
				velocityX := -(2.0 - 5.0 * sqrt((x-0.5)^2 + (y-0.5)^2)) * sin(atan(-(y - 0.5) / (x - 0.5))) + 1.0;
				velocityY := -(2.0 - 5.0 * sqrt((x-0.5)^2 + (y-0.5)^2)) * cos(atan((y - 0.5) / (x - 0.5)));
				velocityZ := 0.0;
				pressure := 9.0 - 4.0 * log(0.2) + 12.5 * ((x-0.5)^2 + (y-0.5)^2) - 20.0 * sqrt((x-0.5)^2 + (y-0.5)^2) + 4.0 * log(sqrt((x-0.5)^2 + (y-0.5)^2));
       	 	}
       	 	else
       	 	{
       	 		density := 1.0;
				velocityX := -(2.0 - 5.0 * sqrt((x-0.5)^2 + (y-0.5)^2)) * sin(atan((y - 0.5) / (x - 0.5))) + 1.0;
				velocityY := (2.0 - 5.0 * sqrt((x-0.5)^2 + (y-0.5)^2)) * cos(atan((y - 0.5) / (x - 0.5)));
				velocityZ := 0.0;
				pressure := 9.0 - 4.0 * log(0.2) + 12.5 * ((x-0.5)^2 + (y-0.5)^2) - 20.0 * sqrt((x-0.5)^2 + (y-0.5)^2) + 4.0 * log(sqrt((x-0.5)^2 + (y-0.5)^2));
       	 	}
        	}
        	else
        	{
			density := 1.0;
			velocityX := 1.0;
			velocityY := 0.0;
			velocityZ := 0.0;
			pressure := 3.0 + 4.0 * log(2.0);
        	}
        	
        	
        	
            </material1>

            <levelSet1>
                phi := 1.0;
            </levelSet1>
        </initialConditions>
    </domain>

   
   
   <materials>
      <numberOfMaterials> 1   </numberOfMaterials>
      <material1>
         <equationOfState>
            <type> StiffenedGas </type>
            <gamma>               1.4   </gamma>
            <A>                   0.0   </A>
            <B>                   0.0   </B>
            <C>                   0.0   </C>
            <rho0>                0.0   </rho0>
            <specificGasConstant> 0.0   </specificGasConstant>
            <backgroundPressure> 0.0 </backgroundPressure>
	      </equationOfState>
         <properties>
            <specificHeatCapacity> 0.0 </specificHeatCapacity>
            <thermalConductivity> 0.0 </thermalConductivity>
            <shearViscosity> 0.0 </shearViscosity>
            <bulkViscosity> 0.0 </bulkViscosity>
         </properties>
      </material1>
   </materials>

    <sourceTerms>
        <gravity>
            <x> 0 </x>
            <y> 0 </y>
            <z> 0 </z>
        </gravity>
    </sourceTerms>

   <multiResolution>
       <maximumLevel> 0 </maximumLevel>

       <refinementCriterion>
           <epsilonReference>    0.01 </epsilonReference>
           
           <levelOfEpsilonReference> 0  </levelOfEpsilonReference>
       </refinementCriterion>
   </multiResolution>

   <timeControl>
      <startTime> 0.0  </startTime>
      <endTime>3.0</endTime>
      <CFLNumber> 0.6 </CFLNumber>
   </timeControl>

   <dimensionalization>
      <lengthReference>       1.0  </lengthReference>
      <velocityReference>     1.0  </velocityReference>
      <densityReference>      1.0  </densityReference>
      <temperatureReference>  1.0  </temperatureReference>
   </dimensionalization>

   <restart>
      <restore>
         <mode>Off</mode> 
         <fileName>None</fileName>
      </restore>
      <snapshots>
         <type>Stamps</type> 
         <interval> 0.01 </interval> 
         <intervalsToKeep> 2 </intervalsToKeep> 
         <stamps>
             <ts1>0.050</ts1>
             <ts2>0.100</ts2>
             <ts3>0.150</ts3>
             <ts4>0.200</ts4>
             <ts5>0.250</ts5>
             <ts6>0.300</ts6>
             <ts7>0.350</ts7>
             <ts8>0.400</ts8>
             <ts9>0.450</ts9>
             <ts10>0.500</ts10>
             <ts11>0.550</ts11>
             <ts12>0.600</ts12>
             <ts13>0.650</ts13>
             <ts14>0.700</ts14>
             <ts15>0.750</ts15>
             <ts16>0.800</ts16>
             <ts17>0.850</ts17>
             <ts18>0.900</ts18>
             <ts19>0.950</ts19>
         </stamps>
      </snapshots>
   </restart>

   <output>
      <timeNamingFactor> 1.e0 </timeNamingFactor>
      <standardOutput> 
         <type> Interval </type> 
         <interval>  0.01 </interval>
	      <stamps>
            <ts1> 0.0004 </ts1>
         </stamps>
      </standardOutput>
      <interfaceOutput> 
         <type> Off </type> 
         <interval>  1e3 </interval>
	      <stamps>
            <ts1>  0.0004 </ts1>
         </stamps>
      </interfaceOutput>
   </output>
</configuration>
